todotxt/__init__.py
todotxt/_dates.py
todotxt/_group.py
todotxt/_todo.py
todotxt/py.typed
todotxt/types.py
todotxt_python-0.3.1.dist-info/METADATA
todotxt_python-0.3.1.dist-info/WHEEL
todotxt_python-0.3.1.dist-info/top_level.txt
todotxt_python-0.3.1.dist-info/RECORD
