Metadata-Version: 2.1
Name: todotxt-python
Version: 0.3.1
Summary: A Python library for working with the todo.txt format.
Home-page: https://github.com/bbugyi200/todotxt
Author: Bryan M Bugyi
Author-email: bryanbugyi34@gmail.com
License: MIT license
Platform: UNKNOWN
Classifier: Development Status :: 3 - Alpha
Classifier: Intended Audience :: Developers
Classifier: License :: OSI Approved :: MIT License
Classifier: Natural Language :: English
Classifier: Programming Language :: Python :: 3
Classifier: Programming Language :: Python :: 3.8
Classifier: Programming Language :: Python :: 3.9
Classifier: Programming Language :: Python :: 3.10
Requires-Python: >=3.8
Requires-Dist: bolton-eris (~=0.2.2)
Requires-Dist: bolton-typist (~=0.1.2)
